sema4ai/build_common/__init__.py
sema4ai/build_common/build_executable.py
sema4ai/build_common/entitlements.py
sema4ai/build_common/file_from_function.py
sema4ai/build_common/process_call.py
sema4ai/build_common/py.typed
sema4ai/build_common/root_dir.py
sema4ai/build_common/signing.py
sema4ai/build_common/version_from_github_actions.py
sema4ai/build_common/workflows.py
sema4ai/build_common/zip_assets.py
sema4ai_build_common-0.0.3.dist-info/METADATA
sema4ai_build_common-0.0.3.dist-info/WHEEL
sema4ai_build_common-0.0.3.dist-info/RECORD
