Metadata-Version: 2.3
Name: sema4ai-build-common
Version: 0.0.3
Summary: Sema4AI Build Common
License: Apache-2.0
Author: Sema4.ai Engineering
Author-email: engineering@sema4.ai
Requires-Python: >=3.11,<4.0
Classifier: License :: OSI Approved :: Apache Software License
Classifier: Programming Language :: Python :: 3
Classifier: Programming Language :: Python :: 3.11
Classifier: Programming Language :: Python :: 3.12
Classifier: Programming Language :: Python :: 3.13
Project-URL: Repository, https://github.com/Sema4AI/actions/
